fcbyk/__init__.py
fcbyk/cli.py
fcbyk/cli_support/__init__.py
fcbyk/cli_support/callbacks.py
fcbyk/cli_support/guard.py
fcbyk/cli_support/gui.py
fcbyk/cli_support/helpers.py
fcbyk/cli_support/output.py
fcbyk/commands/__init__.py
fcbyk/commands/alias.py
fcbyk/commands/ai/__init__.py
fcbyk/commands/ai/cli.py
fcbyk/commands/ai/renderer.py
fcbyk/commands/ai/service.py
fcbyk/commands/lansend/__init__.py
fcbyk/commands/lansend/cli.py
fcbyk/commands/lansend/controller.py
fcbyk/commands/lansend/service.py
fcbyk/commands/pick/__init__.py
fcbyk/commands/pick/cli.py
fcbyk/commands/pick/controller.py
fcbyk/commands/pick/service.py
fcbyk/commands/slide/__init__.py
fcbyk/commands/slide/cli.py
fcbyk/commands/slide/controller.py
fcbyk/commands/slide/gui_server.py
fcbyk/commands/slide/service.py
fcbyk/gui/__init__.py
fcbyk/gui/__main__.py
fcbyk/gui/app.py
fcbyk/gui/assets/icon.png
fcbyk/gui/core/__init__.py
fcbyk/gui/core/compatibility.py
fcbyk/gui/core/process.py
fcbyk/gui/core/singleton.py
fcbyk/gui/ui/__init__.py
fcbyk/gui/ui/lansend_page.py
fcbyk/gui/ui/main_window.py
fcbyk/gui/ui/pick_items_dialog.py
fcbyk/gui/ui/pick_page.py
fcbyk/gui/ui/resources.py
fcbyk/gui/ui/slide_page.py
fcbyk/gui/utils/__init__.py
fcbyk/utils/__init__.py
fcbyk/utils/common.py
fcbyk/utils/files.py
fcbyk/utils/network.py
fcbyk/utils/storage.py
fcbyk/web/R.py
fcbyk/web/__init__.py
fcbyk/web/app.py
fcbyk/web/dist/lansend.html
fcbyk/web/dist/pick.html
fcbyk/web/dist/slide.html
fcbyk/web/dist/assets/_plugin-vue_export-helper-B2FpY1bO.js
fcbyk/web/dist/assets/lansend-1RmPJXbK.js
fcbyk/web/dist/assets/lansend-Ca1IaQ5_.css
fcbyk/web/dist/assets/pick-CeEklAKS.css
fcbyk/web/dist/assets/pick-D7NjQrpm.js
fcbyk/web/dist/assets/slide-B9qYfLS5.js
fcbyk/web/dist/assets/slide-ButJcaV8.css
fcbyk/web/dist/assets/space-mono-latin-400-normal-Rg4St2Dn.woff2
fcbyk/web/dist/assets/space-mono-latin-400-normal-_3DlpgIW.woff
fcbyk/web/dist/assets/space-mono-latin-ext-400-normal-D4cJI_B-.woff
fcbyk_cli-0.2.2.dist-info/licenses/LICENSE
fcbyk_cli-0.2.2.dist-info/METADATA
fcbyk_cli-0.2.2.dist-info/WHEEL
fcbyk_cli-0.2.2.dist-info/entry_points.txt
fcbyk_cli-0.2.2.dist-info/top_level.txt
fcbyk_cli-0.2.2.dist-info/RECORD
