Metadata-Version: 2.4
Name: fcbyk-cli
Version: 0.2.2
Summary: A CLI tool for fcbyk
Author: fcbyk
Author-email: 731240932@qq.com
License: MIT
Classifier: Development Status :: 3 - Alpha
Classifier: Intended Audience :: Developers
Classifier: License :: OSI Approved :: MIT License
Classifier: Programming Language :: Python :: 3
Classifier: Programming Language :: Python :: 3.6
Classifier: Programming Language :: Python :: 3.7
Classifier: Programming Language :: Python :: 3.8
Classifier: Programming Language :: Python :: 3.9
Classifier: Programming Language :: Python :: 3.10
Classifier: Programming Language :: Python :: 3.11
Classifier: Programming Language :: Python :: 3.12
Classifier: Programming Language :: Python :: 3.13
Requires-Python: >=3.6
License-File: LICENSE
Requires-Dist: click>=8; python_version >= "3.7"
Requires-Dist: click<8.0; python_version < "3.7"
Requires-Dist: rich>=10.0.0
Requires-Dist: flask>=2.0; python_version >= "3.7"
Requires-Dist: flask<2.1; python_version < "3.7"
Requires-Dist: dataclasses; python_version < "3.7"
Requires-Dist: flask-socketio==5.3.3
Requires-Dist: python-socketio==5.9.0
Requires-Dist: pyperclip<2.0.0,>=1.9.0
Requires-Dist: importlib-metadata>=4.8.0; python_version < "3.8"
Requires-Dist: requests>=2.28.0; python_version >= "3.7"
Requires-Dist: requests>=2.27.0; python_version < "3.7"
Requires-Dist: pyautogui<1.0.0,>=0.9.50
Requires-Dist: psutil==5.8.0; python_version < "3.12"
Requires-Dist: psutil>=5.9.0; python_version >= "3.12"
Requires-Dist: waitress>=2.0.0
Provides-Extra: test
Requires-Dist: pytest<8.0.0,>=7.0.0; extra == "test"
Requires-Dist: pytest-cov<5.0.0,>=4.0.0; extra == "test"
Requires-Dist: beautifulsoup4<4.11.0,>=4.10.0; extra == "test"
Provides-Extra: gui
Requires-Dist: PySide6>=6.0.0; python_version >= "3.7" and extra == "gui"
Requires-Dist: PyQt5<6; python_version < "3.7" and extra == "gui"
Dynamic: license-file
